shinylive_auth.py
shinylive_auth-2024.7.18.dist-info/LICENSE
shinylive_auth-2024.7.18.dist-info/METADATA
shinylive_auth-2024.7.18.dist-info/WHEEL
shinylive_auth-2024.7.18.dist-info/top_level.txt
shinylive_auth-2024.7.18.dist-info/RECORD
